kimkit/__init__.py
kimkit/default-environment
kimkit/kimcodes.py
kimkit/metadata.py
kimkit/models.py
kimkit/users.py
kimkit/settings/__init__.py
kimkit/settings/metadata_config.edn
kimkit/src/__init__.py
kimkit/src/config.py
kimkit/src/kimapi.py
kimkit/src/kimobjects.py
kimkit/src/logger.py
kimkit/src/mongodb.py
kimkit/src/provenance.py
kimkit/tests/EAM_Dynamo_AcklandTichyVitek_1987_Ag__MO_212700056563_005.txz
kimkit/tests/EAM_Dynamo__MD_120291908751_005.txz
kimkit/tests/__init__.py
kimkit/tests/test_models.py
kimkit-1.1.0.dist-info/licenses/LICENSE
kimkit-1.1.0.dist-info/METADATA
kimkit-1.1.0.dist-info/WHEEL
kimkit-1.1.0.dist-info/top_level.txt
kimkit-1.1.0.dist-info/RECORD
