Metadata-Version: 2.4
Name: kimkit
Version: 1.1.0
Author: Claire Waters
Author-email: Claire Waters <bwaters@umn.edu>
License-Expression: Apache-2.0 WITH LLVM-exception
Requires-Python: >=3.9
License-File: LICENSE
Requires-Dist: pytz
Requires-Dist: kim_edn
Requires-Dist: packaging
Requires-Dist: pygments
Requires-Dist: pymongo
Requires-Dist: numpy
Dynamic: author
Dynamic: license-file
